<?xml version="1.0" encoding="utf-8" ?><dwsync><file name="10best 01-2.jpg" server="ssh.phx.nearlyfreespeech.net" local="3606684122" remote="3704032950" Dst="-1" /><file name="10best 01.jpg" server="ssh.phx.nearlyfreespeech.net" local="3606665534" remote="3704032951" Dst="-1" /><file name="1Social Media Icons-02.svg" server="ssh.phx.nearlyfreespeech.net" local="3606665072" remote="3704032952" Dst="-1" /><file name="1Social Media Icons-02-2.svg" server="ssh.phx.nearlyfreespeech.net" local="3606665084" remote="3704032952" Dst="-1" /><file name="yuumei04.jpg" server="ssh.phx.nearlyfreespeech.net" local="3605449882" remote="3704032953" Dst="-1" /><file name="yuumei05.jpg" server="ssh.phx.nearlyfreespeech.net" local="3605449898" remote="3704032954" Dst="-1" /><file name="1Social Media Icons-03.svg" server="ssh.phx.nearlyfreespeech.net" local="3606665120" remote="3704032954" Dst="-1" /><file name="1header stripe2.eps" server="ssh.phx.nearlyfreespeech.net" local="3606674178" remote="3704032955" Dst="-1" /><file name="1Social Media Icons-01.svg" server="ssh.phx.nearlyfreespeech.net" local="3606665050" remote="3704032956" Dst="-1" /><file name="10best 02.jpg" server="ssh.phx.nearlyfreespeech.net" local="3606665548" remote="3704032957" Dst="-1" /><file name="yuumei07.png" server="ssh.phx.nearlyfreespeech.net" local="3605449940" remote="3704032957" Dst="-1" /><file name="yuumei06.jpg" server="ssh.phx.nearlyfreespeech.net" local="3605449922" remote="3704032958" Dst="-1" /><file name="10best 03-2.jpg" server="ssh.phx.nearlyfreespeech.net" local="3606684188" remote="3704032959" Dst="-1" /><file name="10best 03.jpg" server="ssh.phx.nearlyfreespeech.net" local="3606665606" remote="3704032960" Dst="-1" /><file name="1Footer Pattern.eps" server="ssh.phx.nearlyfreespeech.net" local="3606664548" remote="3704032961" Dst="-1" /><file name="1Social Media Icons-04-2.svg" server="ssh.phx.nearlyfreespeech.net" local="3606665110" remote="3704032962" Dst="-1" /><file name="eventsbanner1.eps" server="ssh.phx.nearlyfreespeech.net" local="3606672174" remote="3704032963" Dst="-1" /><file name="10best 07.jpg" server="ssh.phx.nearlyfreespeech.net" local="3606665580" remote="3704032964" Dst="-1" /><file name="1Social Media Icons-04.svg" server="ssh.phx.nearlyfreespeech.net" local="3606665098" remote="3704032964" Dst="-1" /><file name="yuumei02.jpg" server="ssh.phx.nearlyfreespeech.net" local="3605449842" remote="3704032964" Dst="-1" /><file name="10best 07-2.jpg" server="ssh.phx.nearlyfreespeech.net" local="3606684304" remote="3704032965" Dst="-1" /><file name="yuumei03.jpg" server="ssh.phx.nearlyfreespeech.net" local="3605449862" remote="3704032966" Dst="-1" /><file name="10best 06.jpg" server="ssh.phx.nearlyfreespeech.net" local="3606665586" remote="3704032967" Dst="-1" /><file name="10best 04.jpg" server="ssh.phx.nearlyfreespeech.net" local="3606665600" remote="3704032967" Dst="-1" /><file name="eventsbanner2.eps" server="ssh.phx.nearlyfreespeech.net" local="3606675966" remote="3704032968" Dst="-1" /><file name="10best 10.jpg" server="ssh.phx.nearlyfreespeech.net" local="3606665556" remote="3704032969" Dst="-1" /><file name="yuumei01.jpg" server="ssh.phx.nearlyfreespeech.net" local="3605449816" remote="3704032970" Dst="-1" /><file name="10best 05-2.jpg" server="ssh.phx.nearlyfreespeech.net" local="3606684244" remote="3704032971" Dst="-1" /><file name="10best 05.jpg" server="ssh.phx.nearlyfreespeech.net" local="3606665594" remote="3704032973" Dst="-1" /><file name="10best 02-2.jpg" server="ssh.phx.nearlyfreespeech.net" local="3606684164" remote="3704032974" Dst="-1" /><file name="1Social Media Icons-01-2.svg" server="ssh.phx.nearlyfreespeech.net" local="3606665062" remote="3704032974" Dst="-1" /><file name="homebanner.png" server="ssh.phx.nearlyfreespeech.net" local="3606596312" remote="3704032975" Dst="-1" /><file name="1Social Media Icons-03-2.svg" server="ssh.phx.nearlyfreespeech.net" local="3606665134" remote="3704032975" Dst="-1" /><file name="1AD CC 2018.jpg" server="ssh.phx.nearlyfreespeech.net" local="3604592378" remote="3704032976" Dst="-1" /><file name="1favicon.svg" server="ssh.phx.nearlyfreespeech.net" local="3606764792" remote="3704032976" Dst="-1" /><file name="1headerbanner.png" server="ssh.phx.nearlyfreespeech.net" local="3606587808" remote="3704032976" Dst="-1" /><file name="Resources banner.jpg" server="ssh.phx.nearlyfreespeech.net" local="3605451156" remote="3704032977" Dst="-1" /><file name="10best 04-2.jpg" server="ssh.phx.nearlyfreespeech.net" local="3606684210" remote="3704032978" Dst="-1" /><file name="10best 06-2.jpg" server="ssh.phx.nearlyfreespeech.net" local="3606684268" remote="3704032979" Dst="-1" /><file name="Events banner.jpg" server="ssh.phx.nearlyfreespeech.net" local="3605460442" remote="3704032979" Dst="-1" /><file name="1WEBSITE LOGO.svg" server="ssh.phx.nearlyfreespeech.net" local="3606664920" remote="3704032980" Dst="-1" /><file name="10best 08-2.jpg" server="ssh.phx.nearlyfreespeech.net" local="3606684342" remote="3704032980" Dst="-1" /><file name="10best Banner Image.png" server="ssh.phx.nearlyfreespeech.net" local="3606585482" remote="3704032981" Dst="-1" /><file name="homebanner.eps" server="ssh.phx.nearlyfreespeech.net" local="3606596302" remote="3704032982" Dst="-1" /><file name="1Social Media Icons-04.eps" server="ssh.phx.nearlyfreespeech.net" local="3604685738" remote="3704032983" Dst="-1" /><file name="1headerbanner.eps" server="ssh.phx.nearlyfreespeech.net" local="3606587800" remote="3704032983" Dst="-1" /><file name="1Social Media Icons-01.eps" server="ssh.phx.nearlyfreespeech.net" local="3604685738" remote="3704032984" Dst="-1" /><file name="1Social Media Icons-03.eps" server="ssh.phx.nearlyfreespeech.net" local="3604685738" remote="3704032985" Dst="-1" /><file name="1Social Media Icons-02.eps" server="ssh.phx.nearlyfreespeech.net" local="3604685738" remote="3704032986" Dst="-1" /><file name="1footerbanner2.eps" server="ssh.phx.nearlyfreespeech.net" local="3606595636" remote="3704032986" Dst="-1" /><file name="10best 08.jpg" server="ssh.phx.nearlyfreespeech.net" local="3606665570" remote="3704032987" Dst="-1" /><file name="10best 09-2.jpg" server="ssh.phx.nearlyfreespeech.net" local="3606684382" remote="3704032988" Dst="-1" /><file name="yuumei banner.jpg" server="ssh.phx.nearlyfreespeech.net" local="3606597642" remote="3704032988" Dst="-1" /><file name="1header stripe2.png" server="ssh.phx.nearlyfreespeech.net" local="3606596558" remote="3704032988" Dst="-1" /><file name="10best 10-2.jpg" server="ssh.phx.nearlyfreespeech.net" local="3606684420" remote="3704032989" Dst="-1" /><file name="10best 09.jpg" server="ssh.phx.nearlyfreespeech.net" local="3606665564" remote="3704032990" Dst="-1" /><file name="Home Banner 04.jpg" server="ssh.phx.nearlyfreespeech.net" local="3606308434" remote="3704032990" Dst="-1" /><file name="1Footer Pattern.jpg" server="ssh.phx.nearlyfreespeech.net" local="3606664564" remote="3704032991" Dst="-1" /><file name="1favicon.eps" server="ssh.phx.nearlyfreespeech.net" local="3606764750" remote="3704032991" Dst="-1" /><file name="eventsbanner1.png" server="ssh.phx.nearlyfreespeech.net" local="3606672216" remote="3704032992" Dst="-1" /><file name="Home Banner 01.jpg" server="ssh.phx.nearlyfreespeech.net" local="3604590870" remote="3704032993" Dst="-1" /><file name="eventsbanner2.png" server="ssh.phx.nearlyfreespeech.net" local="3606675976" remote="3704032993" Dst="-1" /><file name="Home Banner 02.jpg" server="ssh.phx.nearlyfreespeech.net" local="3606308386" remote="3704032994" Dst="-1" /><file name="1WEBSITE LOGO.ai" server="ssh.phx.nearlyfreespeech.net" local="3606588270" remote="3704032994" Dst="-1" /><file name="yuumei08.png" server="ssh.phx.nearlyfreespeech.net" local="3605450024" remote="3704032995" Dst="-1" /><file name="Home Banner 03.jpg" server="ssh.phx.nearlyfreespeech.net" local="3606308426" remote="3704032995" Dst="-1" /><file name="yuumei09.jpg" server="ssh.phx.nearlyfreespeech.net" local="3605450046" remote="3704032996" Dst="-1" /></dwsync>